LICENSE
README.md
setup.py
ofrak_capstone/__init__.py
ofrak_capstone/components.py
ofrak_capstone/disassembler_service_capstone.py
ofrak_capstone.egg-info/PKG-INFO
ofrak_capstone.egg-info/SOURCES.txt
ofrak_capstone.egg-info/dependency_links.txt
ofrak_capstone.egg-info/entry_points.txt
ofrak_capstone.egg-info/requires.txt
ofrak_capstone.egg-info/top_level.txt
ofrak_capstone_test/__init__.py
ofrak_capstone_test/test_ofrak_capstone.py