Metadata-Version: 2.1
Name: ofrak-capstone
Version: 1.0.0
Home-page: https://ofrak.com/
Download-URL: https://github.com/redballoonsecurity/ofrak
Author: Red Balloon Security
Author-email: ofrak@redballoonsecurity.com
License: Proprietary
Project-URL: Documentation, https://ofrak.com/docs/
Project-URL: Community License, https://github.com/redballoonsecurity/ofrak/blob/master/LICENSE
Project-URL: Commercial Licensing Information, https://ofrak.com/license/
Classifier: Programming Language :: Python :: 3
Classifier: Operating System :: OS Independent
Classifier: License :: Other/Proprietary License
Classifier: License :: Free To Use But Restricted
Classifier: License :: Free For Home Use
Classifier: Topic :: Security
Classifier: Typing :: Typed
Requires-Python: >=3.7
Provides-Extra: test
License-File: LICENSE
